setup.py
sk_automation/__init__.py
sk_automation/auto_model.py
sk_automation/data_pretreatment.py
sk_automation/feature_analysis.py
sk_automation/feature_project.py
sk_automation/function.py
sk_automation/model_build.py
sk_automation/setup.py
sk_automation.egg-info/PKG-INFO
sk_automation.egg-info/SOURCES.txt
sk_automation.egg-info/dependency_links.txt
sk_automation.egg-info/top_level.txt