Metadata-Version: 2.1
Name: sk-automation
Version: 1.0.5
Summary: Auto Model
Home-page: UNKNOWN
License: UNKNOWN
Platform: UNKNOWN
